ada_prosperity3_backtest/__init__.py
ada_prosperity3_backtest/backtest.py
ada_prosperity3_backtest/cli.py
ada_prosperity3_backtest/datamodel.py
ada_prosperity3_backtest/df_to_states.py
ada_prosperity3_backtest/log_to_states.py
ada_prosperity3_backtest/logic.py
ada_prosperity3_backtest/test.py
ada_prosperity3_backtest/data/__init__.py
ada_prosperity3_backtest/data/round0/__init__.py
ada_prosperity3_backtest/data/round0/day0/__init__.py
ada_prosperity3_backtest/data/round0/day0/prices00.csv
ada_prosperity3_backtest/data/round0/day0/trades00.csv
ada_prosperity3_backtest/data/round1/__init__.py
ada_prosperity3_backtest/data/round2/__init__.py
ada_prosperity3_backtest/data/round3/__init__.py
ada_prosperity3_backtest/data/round4/__init__.py
ada_prosperity3_backtest/data/round5/__init__.py
ada_prosperity3_backtest/env/__init__.py
ada_prosperity3_backtest/env/datamodel.py
ada_prosperity3_backtest-0.1.6.dist-info/LICENSE
ada_prosperity3_backtest-0.1.6.dist-info/METADATA
ada_prosperity3_backtest-0.1.6.dist-info/WHEEL
ada_prosperity3_backtest-0.1.6.dist-info/entry_points.txt
ada_prosperity3_backtest-0.1.6.dist-info/top_level.txt
ada_prosperity3_backtest-0.1.6.dist-info/RECORD
