Metadata-Version: 2.2
Name: ada-prosperity3-backtest
Version: 0.1.6
Summary: Backtest tool for Prosperity-3 trading competition, by team ADA Refactor.
Author-email: Yanxu Chen <alphagem618@gmail.com>
License: MIT License
License-File: LICENSE
Requires-Dist: pandas
